{
  "events": [
    { "time": "20:45", "label": "Inizio serata"},
    { "time": "20:48", "label": "Olly canta Balorda Nostalgia"},
    { "time": "20:55", "label": "Ingresso Laura Pausini"},
    { "time": "20:59", "label": "esibizione: Ditonellapiaga"},
    { "time": "21:05", "label": "esibizione: Michele Bravi"},
    { "time": "21:10", "label": "esibizione: Sayf"},
    { "time": "21:15", "label": "esibizione: Mara Sattei"},
    { "time": "21:21", "label": "esibizione: Dargen D'Amico"},
    { "time": "21:30", "label": "Omaggio a Beppe Vessicchio"},
    { "time": "21:34", "label": "esibizione: Arisa"},
    { "time": "21:44", "label": "esibizione Luchè"},
    { "time": "21:52", "label": "105 anni e non sentirli"},
    { "time": "22:02", "label": "esibizione: Tommaso Paradiso"},
    { "time": "22:08", "label": "esibizione: Elettra Lamborghini"},
    { "time": "22:16", "label": "esibizione: Patty Pravo"},
    { "time": "22:21", "label": "esibizione: Samurai Jay"},
    { "time": "22:30", "label": "Tiziano Ferro"},
    { "time": "22:47", "label": "esibizione: RAF"},
    { "time": "22:56", "label": "Laura Pausini cambia abito"},
    { "time": "22:59", "label": "esibizione: J-Ax"},
    { "time": "23:05", "label": "Collegamento con Gaia"},
    { "time": "23:10", "label": "esibizione: Fulminacci"},
    { "time": "23:19", "label": "esibizione: Levante"},
    { "time": "23:24", "label": "esibizione: Fedez & Masini"},
    { "time": "23:29", "label": "esibizione: Ermal Meta"},
    { "time": "23:35", "label": "Collegamento con Max Pezzali"},
    { "time": "23:46", "label": "esibizione: Serena Brancale"},
    { "time": "23:54", "label": "Kabir Bedi"},
    { "time": "00:04", "label": "esibizione: Nayt"},
    { "time": "00:09", "label": "esibizione: Malika Ayane"},
    { "time": "00:14", "label": "esibizione: Eddie Brock"},
    { "time": "00:17", "label": "esibizione: Sal Da Vinci"},
    { "time": "00:29", "label": "esibizione: Enrico Nigiotti"},
    { "time": "00:30", "label": "Laura Pausini cambia abito"},
    { "time": "00:38", "label": "esibizione: Tredici Pietro"},
    { "time": "00:44", "label": "esibizione: Chiello"},
    { "time": "00:54", "label": "esibizione: Le bambole di pezza"},
    { "time": "01:01", "label": "esibizione: Maria Antonietta & Colombre"},
    { "time": "01:06", "label": "esibizione: Leo Gassman"},
    { "time": "01:12", "label": "esibizione: Francesco Renga"},
    { "time": "01:16", "label": "esibizione: LDA & AKA7even"},
    { "time": "01:30", "label": "Annuncio della top 5"}
  ]
}
